[{"bottomright": {"x": 550, "y": 315}, "topleft": {"x": 364, "y": 325}, "id": 1, "label": "person"}, {"bottomright": {"x": 827, "y": 51}, "topleft": {"x": 318, "y": 221}, "id": 1, "label": "person"}, {"bottomright": {"x": 655, "y": 74}, "topleft": {"x": 276, "y": 215}, "id": 1, "label": "person"}, {"bottomright": {"x": 998, "y": 6}, "topleft": {"x": 391, "y": 239}, "id": 1, "label": "person"}, {"bottomright": {"x": 408, "y": 53}, "topleft": {"x": 193, "y": 225}, "id": 1, "label": "person"}, {"bottomright": {"x": 548, "y": 277}, "topleft": {"x": 249, "y": 318}, "id": 1, "label": "person"}, {"bottomright": {"x": 238, "y": 142}, "topleft": {"x": 151, "y": 299}, "id": 1, "label": "person"}]