[{"bottomright": {"x": 761, "y": 66}, "topleft": {"x": 344, "y": 299}, "id": 1, "label": "person"}, {"bottomright": {"x": 516, "y": 317}, "topleft": {"x": 265, "y": 287}, "id": 1, "label": "person"}, {"bottomright": {"x": 557, "y": 188}, "topleft": {"x": 218, "y": 208}, "id": 1, "label": "person"}, {"bottomright": {"x": 72, "y": 82}, "topleft": {"x": 76, "y": 194}, "id": 1, "label": "person"}, {"bottomright": {"x": 310, "y": 341}, "topleft": {"x": 189, "y": 287}, "id": 1, "label": "person"}, {"bottomright": {"x": 1098, "y": 181}, "topleft": {"x": 415, "y": 250}, "id": 1, "label": "person"}]