[{"bottomright": {"x": 627, "y": 216}, "topleft": {"x": 991, "y": 571}, "id": 1, "label": "person"}, {"bottomright": {"x": 423, "y": 50}, "topleft": {"x": 594, "y": 301}, "id": 1, "label": "person"}, {"bottomright": {"x": 184, "y": 27}, "topleft": {"x": 283, "y": 328}, "id": 1, "label": "person"}, {"bottomright": {"x": 419, "y": 218}, "topleft": {"x": 697, "y": 487}, "id": 1, "label": "person"}, {"bottomright": {"x": 890, "y": 247}, "topleft": {"x": 1203, "y": 536}, "id": 1, "label": "person"}, {"bottomright": {"x": 337, "y": 40}, "topleft": {"x": 478, "y": 309}, "id": 1, "label": "person"}, {"bottomright": {"x": 1106, "y": 25}, "topleft": {"x": 1238, "y": 240}, "id": 1, "label": "person"}, {"bottomright": {"x": 660, "y": 34}, "topleft": {"x": 755, "y": 256}, "id": 1, "label": "person"}]